influx_rust/__init__.py
influx_rust/influx_rust.abi3.so
influx_rust-0.1.1.dist-info/METADATA
influx_rust-0.1.1.dist-info/WHEEL
influx_rust-0.1.1.dist-info/RECORD
