Metadata-Version: 2.4
Name: influx-rust
Version: 0.1.1
Classifier: Development Status :: 4 - Beta
Classifier: Intended Audience :: Developers
Classifier: License :: OSI Approved :: MIT License
Classifier: Programming Language :: Rust
Classifier: Programming Language :: Python :: 3
Classifier: Programming Language :: Python :: 3.8
Classifier: Programming Language :: Python :: 3.9
Classifier: Programming Language :: Python :: 3.10
Classifier: Programming Language :: Python :: 3.11
Classifier: Programming Language :: Python :: 3.12
Classifier: Programming Language :: Python :: Implementation :: CPython
Classifier: Topic :: Database
Classifier: Topic :: Software Development :: Libraries :: Python Modules
Summary: High-performance InfluxDB query interface for Python
Keywords: influxdb,rust,performance,async,database
Author-email: AquaChile <devops@devops.com>
License: MIT
Requires-Python: >=3.8
Project-URL: Documentation, https://github.com/famoralesc/influx-rust/blob/main/README.md
Project-URL: Homepage, https://github.com/famoralesc/influx-rust
Project-URL: Repository, https://github.com/famoralesc/influx-rust
